disk_objectstore/__init__.py
disk_objectstore/backup_utils.py
disk_objectstore/cli.py
disk_objectstore/container.py
disk_objectstore/database.py
disk_objectstore/dataclasses.py
disk_objectstore/exceptions.py
disk_objectstore/py.typed
disk_objectstore/utils.py
disk_objectstore/examples/__init__.py
disk_objectstore/examples/example_objectstore.py
disk_objectstore/examples/profile_zeros.py
disk_objectstore-1.3.0.dist-info/entry_points.txt
disk_objectstore-1.3.0.dist-info/licenses/LICENSE.txt
disk_objectstore-1.3.0.dist-info/WHEEL
disk_objectstore-1.3.0.dist-info/METADATA
disk_objectstore-1.3.0.dist-info/RECORD
