Metadata-Version: 2.4
Name: disk_objectstore
Version: 1.3.0
Summary: An implementation of an efficient object store that writes directly on disk.
Keywords: object store,repository,file store,key-value store
Author: Giovanni Pizzi, Chris Sewell, Sebastiaan P. Huber
Requires-Python: >=3.9
Classifier: Development Status :: 5 - Production/Stable
Classifier: License :: OSI Approved :: MIT License
Classifier: Operating System :: MacOS :: MacOS X
Classifier: Operating System :: Microsoft :: Windows
Classifier: Operating System :: POSIX :: Linux
Classifier: Programming Language :: Python :: 3
Classifier: Programming Language :: Python :: 3.9
Classifier: Programming Language :: Python :: 3.10
Classifier: Programming Language :: Python :: 3.11
Classifier: Programming Language :: Python :: 3.12
Classifier: Programming Language :: Python :: 3.13
Classifier: Programming Language :: Python :: Implementation :: CPython
Classifier: Topic :: Software Development :: Libraries :: Python Modules
License-File: LICENSE.txt
Requires-Dist: click
Requires-Dist: sqlalchemy>=1.4.22
Requires-Dist: coverage ; extra == "dev"
Requires-Dist: pre-commit ; extra == "dev"
Requires-Dist: pytest ; extra == "dev"
Requires-Dist: pytest-benchmark ; extra == "dev"
Requires-Dist: pytest-cov ; extra == "dev"
Requires-Dist: jinja2<3.1 ; extra == "docs"
Requires-Dist: myst-parser~=1.0 ; extra == "docs"
Requires-Dist: sphinx~=5.0.2 ; extra == "docs"
Requires-Dist: sphinx-book-theme~=1.1.3 ; extra == "docs"
Requires-Dist: sphinx-panels~=0.4.1 ; extra == "docs"
Requires-Dist: sphinxext-rediraffe~=0.2.7 ; extra == "docs"
Requires-Dist: memory-profiler ; extra == "examples"
Requires-Dist: profilehooks ; extra == "examples"
Requires-Dist: psutil ; extra == "examples"
Requires-Dist: pywin32 ; extra == "examples" and (platform_system == "Windows")
Requires-Dist: h5py ; extra == "optionaltests"
Requires-Dist: numpy ; extra == "optionaltests"
Requires-Dist: tqdm ; extra == "progressbar"
Project-URL: Source, https://github.com/aiidateam/disk-objectstore
Provides-Extra: dev
Provides-Extra: docs
Provides-Extra: examples
Provides-Extra: optionaltests
Provides-Extra: progressbar
